ldkex/__init__.py
ldkex/archive.py
ldkex/extractor.py
ldkex/geodata.py
ldkex/utils.py
tests/__init__.py
tests/test_integration.py
ldkex-0.3.3.dist-info/METADATA
ldkex-0.3.3.dist-info/WHEEL
ldkex-0.3.3.dist-info/top_level.txt
ldkex-0.3.3.dist-info/RECORD
