Metadata-Version: 2.1
Name: ldkex
Version: 0.3.3
Summary: A library to read .ldk files without color loss
Home-page: https://github.com/adamwoodintel/ldkex
Author: Adam Wood
Author-email: adamwoodintel@gmail.com
Requires-Python: >=3.11
Requires-Dist: setuptools ==70.2.0
Requires-Dist: pytest ==8.2.2
Requires-Dist: milgeo >=0.3.1
Requires-Dist: text-to-sidc >=0.0.13
